infapy/__init__.py
infapy/connections.py
infapy/exceptions.py
infapy/cdi/__init__.py
infapy/v2/__init__.py
infapy/v2/getActivityLog.py
infapy/v2/getActivityMonitor.py
infapy/v2/getAgent.py
infapy/v2/getAuditLog.py
infapy/v2/getRuntimeEnvironment.py
infapy/v2/getSchedule.py
infapy/v2/jobControl.py
infapy/v2/mttask.py
infapy/v2/org.py
infapy/v2/taskList.py
infapy/v2/test.py
infapy/v2/test2.py
infapy/v2/user.py
infapy/v3/__init__.py
infapy/v3/agentService.py
infapy/v3/exportObject.py
infapy/v3/getSecurityLog.py
infapy/v3/importObject.py
infapy/v3/license.py
infapy/v3/objects.py
infapy/v3/schedule.py
infapy/v3/test_suvam_v3.py
infapy/v3/userGroups.py
infapy/v3/userRoles.py
infapy/v3/users.py
infapy-1.0.7.1.dist-info/LICENSE
infapy-1.0.7.1.dist-info/METADATA
infapy-1.0.7.1.dist-info/WHEEL
infapy-1.0.7.1.dist-info/top_level.txt
infapy-1.0.7.1.dist-info/RECORD
