Metadata-Version: 2.1
Name: infapy
Version: 1.0.7.1
Summary: Automation Tool for informatica Cloud
Home-page: UNKNOWN
Author: Prashanth
License: UNKNOWN
Platform: UNKNOWN
Classifier: Programming Language :: Python :: 3
Classifier: License :: OSI Approved :: Apache Software License
Classifier: Operating System :: OS Independent
Requires-Python: >=3.7
License-File: LICENSE
Requires-Dist: requests
Requires-Dist: cryptography
